{
    "Prerequisites": {
        "type": "AND",
        "items": [
            {
                "type": "AND",
                "items": [
                    {
                        "type": "COURSE",
                        "code": "SFM401"
                    },
                    {
                        "type": "COURSE",
                        "code": "SFM402"
                    }
                ]
            },
            {
                "type": "OR",
                "items": [
                    {
                        "type": "PROGRAM",
                        "code": "H-Accounting & Financial Management"
                    },
                    {
                        "type": "PROGRAM",
                        "code": "H-Environment & Business"
                    },
                    {
                        "type": "PROGRAM",
                        "code": "H-Sustainability & Financial Management"
                    }
                ]
            }
        ]
    },
    "Antirequisites": "",
    "Corequisites": ""
}