{
    "Prerequisites": {
        "type": "OR",
        "items": [
            {
                "type": "LEVEL",
                "level": "2A",
                "op": ">="
            },
            {
                "type": "OR",
                "items": [
                    {
                        "type": "PROGRAM",
                        "code": "Peace & Conflict Studies Diploma"
                    }
                ]
            }
        ]
    },
    "Antirequisites": {
        "type": "NOT",
        "items": [
            {
                "type": "COURSE",
                "code": "PACS301 (Topic 12: Refugees and Forced Migration)"
            }
        ]
    },
    "Corequisites": ""
}