{
    "Prerequisites": {
        "type": "OR",
        "items": [
            {
                "type": "AND",
                "items": [
                    {
                        "type": "COURSE",
                        "code": "INTEG420A"
                    }
                ]
            },
            {
                "type": "AND",
                "items": [
                    {
                        "type": "COURSE",
                        "code": "INTEG420"
                    }
                ]
            }
        ]
    },
    "Antirequisites": "",
    "Corequisites": ""
}