{
    "Prerequisites": {
        "type": "OR",
        "items": [
            {
                "type": "LEVEL",
                "level": "2A",
                "op": ">="
            },
            {
                "type": "OR",
                "items": [
                    {
                        "type": "PROGRAM",
                        "code": "H-Computer Engineering"
                    },
                    {
                        "type": "PROGRAM",
                        "code": "H-Electrical Engineering"
                    }
                ]
            }
        ]
    },
    "Antirequisites": {
        "type": "NOT",
        "items": [
            {
                "type": "COURSE",
                "code": "MATH106"
            },
            {
                "type": "COURSE",
                "code": "MATH114"
            },
            {
                "type": "COURSE",
                "code": "MATH115"
            },
            {
                "type": "COURSE",
                "code": "MATH136"
            },
            {
                "type": "COURSE",
                "code": "MATH146"
            },
            {
                "type": "COURSE",
                "code": "NE112"
            }
        ]
    },
    "Corequisites": ""
}